README.md
setup.py
ch_frb_wview_test_1.egg-info/PKG-INFO
ch_frb_wview_test_1.egg-info/SOURCES.txt
ch_frb_wview_test_1.egg-info/dependency_links.txt
ch_frb_wview_test_1.egg-info/requires.txt
ch_frb_wview_test_1.egg-info/top_level.txt
webapp/__init__.py
webapp/chime_frb_operations.py
webapp/chime_frb_operations_interface.py
webapp/chlog_database.py
webapp/cnc_client.py
webapp/cnc_ssh.py
webapp/webapp.py